{"singlePage": [], "startSite": "", "filingNum": "", "onePageListNum": 15, "commentLabelColor": "#006b75", "yearColorList": ["#bc4c00", "#0969da", "#1f883d", "#A333D0"], "i18n": "CN", "themeMode": "manual", "dayTheme": "light", "nightTheme": "dark", "urlMode": "pinyin", "script": "", "style": "", "head": "", "indexScript": "", "indexStyle": "", "bottomText": "", "showPostSource": 1, "iconList": {}, "UTC": 8, "rssSplit": "sentence", "exlink": {}, "needComment": 1, "allHead": "", "title": "\u82d7\u5f18\u6587-\u6768\u5929\u5929\u7684\u535a\u5ba2", "subTitle": "\u5206\u4eab\u70b9\u5565\u597d\u5462\u2026\u2026", "avatarUrl": "https://avatars.githubusercontent.com/u/179659172?v=4", "GMEEK_VERSION": "last", "postListJson": {"P1": {"htmlDir": "docs/post/ce-shi.html", "labels": ["documentation"], "postTitle": "\u6d4b\u8bd5", "postUrl": "post/ce-shi.html", "postSourceUrl": "https://github.com/MHW-YTT/mhw-ytt.github.io/issues/1", "commentNum": 0, "wordCount": 4, "description": "\u6d4b\u8bd5\u4e00\u4e0b\u3002", "top": 0, "createdAt": 1724807827, "style": "", "script": "", "head": "", "ogImage": "https://avatars.githubusercontent.com/u/179659172?v=4", "createdDate": "2024-08-28", "dateLabelColor": "#bc4c00"}, "P2": {"htmlDir": "docs/post/7-zip-xia-zai.html", "labels": ["documentation"], "postTitle": "7-zip\u4e0b\u8f7d", "postUrl": "post/7-zip-xia-zai.html", "postSourceUrl": "https://github.com/MHW-YTT/mhw-ytt.github.io/issues/2", "commentNum": 0, "wordCount": 57, "description": "https://www.123pan.com/s/EFv6Vv-rB3AA\r\n\r\n\u81ea\u5df1\u53bb\u4e0b\u8f7d\u5427\uff0c\u662f\u4ece\u5b98\u65b9\u7f51\u7ad9\u4e0b\u8f7d\u7684\u3002", "top": 0, "createdAt": 1724808996, "style": "", "script": "", "head": "", "ogImage": "https://avatars.githubusercontent.com/u/179659172?v=4", "createdDate": "2024-08-28", "dateLabelColor": "#bc4c00"}, "P3": {"htmlDir": "docs/post/OBS Studio 30.2.0.html", "labels": ["documentation"], "postTitle": "OBS Studio 30.2.0", "postUrl": "post/OBS%20Studio%2030.2.0.html", "postSourceUrl": "https://github.com/MHW-YTT/mhw-ytt.github.io/issues/3", "commentNum": 0, "wordCount": 59, "description": "\u4e0b\u8f7d\u94fe\u63a5\r\nhttps://www.123pan.com/s/EFv6Vv-VI3AA\r\n\r\n\u81ea\u5df1\u5b89\u88c5\uff0c\u6765\u6e90\u4e8e\u5b98\u7f51\r\n\u3002", "top": 0, "createdAt": 1725000654, "style": "", "script": "", "head": "", "ogImage": "https://avatars.githubusercontent.com/u/179659172?v=4", "createdDate": "2024-08-30", "dateLabelColor": "#bc4c00"}}, "singeListJson": {}, "labelColorDict": {"bug": "#d73a4a", "documentation": "#0075ca", "duplicate": "#cfd3d7", "enhancement": "#a2eeef", "good first issue": "#7057ff", "help wanted": "#008672", "invalid": "#e4e669", "question": "#d876e3", "wontfix": "#ffffff"}, "displayTitle": "\u82d7\u5f18\u6587-\u6768\u5929\u5929\u7684\u535a\u5ba2", "faviconUrl": "https://avatars.githubusercontent.com/u/179659172?v=4", "ogImage": "https://avatars.githubusercontent.com/u/179659172?v=4", "primerCSS": "<link href='https://mirrors.sustech.edu.cn/cdnjs/ajax/libs/Primer/21.0.7/primer.css' rel='stylesheet' />", "homeUrl": "https://mhw-ytt.github.io", "prevUrl": "disabled", "nextUrl": "disabled"}